Metadata-Version: 1.1
Name: django-static-md5url
Version: 0.1
Summary: Versioning django static files in production. Add md5 suffix to url
Home-page: https://github.com/saladrai/django-static-md5url
Author: Saladraj Eugene
Author-email: saladrai@gmail.com
License: MIT
Keywords: django static md5url
Platform: UNKNOWN
Classifier: Environment :: Web Environment
Classifier: Framework :: Django
Classifier: Intended Audience :: Developers
Classifier: License :: OSI Approved :: MIT License
Classifier: Operating System :: OS Independent
Classifier: Programming Language :: Python
Classifier: Programming Language :: Python :: 3
Classifier: Topic :: Internet :: WWW/HTTP
Classifier: Topic :: Software Development :: Libraries :: Python Modules
